pizdets/Experiment.py
pizdets/ExperimentFiles.py
pizdets/ExperimentNew.py
pizdets/__init__.py
pizdets/_dose_controller.py
pizdets/_loop.py
pizdets/_plotter.py
pizdets/loop.py
pizdets/threadingtest.py
pizdets/pm/__init__.py
pizdets/pm/device_messages_pb2.py
pizdets/pm/network_messages_pb2.py
pizdets/pm/protobuf_to_dict.py
pizdets-0.40.37.dist-info/METADATA
pizdets-0.40.37.dist-info/WHEEL
pizdets-0.40.37.dist-info/top_level.txt
pizdets-0.40.37.dist-info/zip-safe
pizdets-0.40.37.dist-info/RECORD
